minty_infra_sqlalchemy/__init__.py
minty_infra_sqlalchemy/json_encoder.py
minty_infra_sqlalchemy/py.typed
minty_infra_sqlalchemy-3.2.0.dist-info/METADATA
minty_infra_sqlalchemy-3.2.0.dist-info/WHEEL
minty_infra_sqlalchemy-3.2.0.dist-info/top_level.txt
minty_infra_sqlalchemy-3.2.0.dist-info/RECORD
