Metadata-Version: 2.1
Name: minty-infra-sqlalchemy
Version: 3.2.0
Summary: SQLAlchemy infrastructure for Minty
Home-page: https://gitlab.com/minty-python/minty-infra-sqlalchemy
Author: Martijn van de Streek
Author-email: martijn@mintlab.nl
License: EUPL license
Keywords: minty_infra_sqlalchemy
Platform: UNKNOWN
Classifier: Development Status :: 5 - Production/Stable
Classifier: Intended Audience :: Developers
Classifier: License :: OSI Approved :: European Union Public Licence 1.2 (EUPL 1.2)
Classifier: Natural Language :: English
Classifier: Programming Language :: Python :: 3.9
Requires-Dist: minty (~=3.0)
Requires-Dist: sqlalchemy (<2.0.0,>=1.4.0)
Requires-Dist: setuptools (~=65.6)
